{"date":"2013-11-19T18:11:01Z","user":"ejfox","posts":[{"href":"http://allthingsd.com/20131119/teardown-shows-sonys-playstation-4-costs-381-to-build/","description":"Sony's PlayStation 4 Costs $381 to Build, Only $18 Under Retail Price - Arik Hesseldahl - Media - AllThingsD","extended":"RT @newsycombinator: PS4 costs $381 to build in teardown – only $18 less than retail price ","meta":"b3744f41809b64bf39e75d8dbdf6c7db","hash":"949815c6f414de4b8dc642e3f3e856c1","time":"2013-11-19T18:11:01Z","shared":"yes","toread":"no","tags":""}]}