{"date":"2015-03-18T16:45:53Z","user":"ejfox","posts":[{"href":"http://www.nytimes.com/interactive/2015/03/19/upshot/3d-yield-curve-economic-growth.html?_r=2","description":"Log In - The New York Times","extended":"RT @blprnt: My, oh my - Amanda Cox and @driven_by_data bring the MUTHAF&!*ING 3RD DIMENSION to the @nytimes: ","meta":"00d1305ac15df99f4a4da10cd45ea643","hash":"f784a9005ef4c3257067ef429b4247e5","time":"2015-03-18T16:45:53Z","shared":"yes","toread":"no","tags":""},{"href":"https://twitter.com/rachelbinx/status/578324677191294977/photo/1","description":"rachel binx on Twitter: \"naming advice please: how would you refer to these three styles? What I have so far is: stacked, shared, dual. http://t.co/XCWqmRXQRV\"","extended":"naming advice please: how would you refer to these three styles? What I have so far is: stacked, shared, dual. ","meta":"a76bf89a6ab4840e83a55392f04a64f9","hash":"29750c13820a453266ed350a94e48c64","time":"2015-03-18T22:38:42Z","shared":"yes","toread":"no","tags":""}]}