{"date":"2018-12-14T02:57:38Z","user":"ejfox","posts":[{"href":"https://davidneat.wordpress.com/2015/05/03/a-quick-guide-to-soldering-brass/amp/","description":"A quick guide to soldering brass – davidneat","extended":"https://twitter.com/davedarko/status/1072076882957484033","meta":"0f6deedb5cc0461ed90419c12d73f61a","hash":"19a83379433b41cf536d094275a8d5d0","time":"2018-12-14T02:57:38Z","shared":"yes","toread":"no","tags":"art resource howto"},{"href":"http://www.papiermache.co.uk/tutorials/giant-head/3/","description":"Papier Mache - Tutorials - Giant head","extended":"Start to papier mache.\r\n\r\nNote: I prefer to use kraft paper, but any paper will do. I also prefer to make my glue hot: 3 parts boiling water to 1 part flour + 1/4 cup salt (adding flour/salt to water slowly mixing using a hand blender). I then papier mache like crazy until the glue cools down (and then I stop!)","meta":"94352505d0f94122f70fc85b4f09716a","hash":"f9cf2e71e61f870f60dde107768f17c8","time":"2018-12-14T03:19:36Z","shared":"yes","toread":"no","tags":"art reference howto"},{"href":"https://www.nybooks.com/daily/2018/12/13/american-women-of-the-far-right/","description":"American Women of the Far Right | by Glenna Gordon | NYR Daily | The New York Review of Books","extended":"To be in the Klan is to believe that you live in an unfair world where you’ve been deprived of what’s rightfully yours and everyone is your enemy except these people who wear the same robes and the same secret Klan words. These people are your friends. When they all dress up together, they perform rituals that make them feel important, remind them of their membership and of their enemies, who are lurking everywhere except for the group encircled around that burning cross. They call their rallies “Lightings,” not burnings. While they’re intended to inspire terror, they’re also opportunities for family picnics.","meta":"a9b3cfcdf7f1f8fc434d490bb6b1cae8","hash":"5ee4beb285d1720ab0f6c11c6a3e396f","time":"2018-12-14T03:22:18Z","shared":"yes","toread":"no","tags":"politics"}]}