{"date":"2019-12-02T01:25:55Z","user":"ejfox","posts":[{"href":"https://www.ikea.com/us/en/p/trollberget-sit-stand-support-grann-beige-40388264/","description":"TROLLBERGET Sit/stand support - Grann beige - IKEA","extended":"Moves you when seated. This sit/stand support helps you to sit actively. A smart mechanism keeps your body in constant motion, strengthens muscles and the spine – and gives you a naturally healthy posture.","meta":"70886ae0c59527cc25b449cc254bc4a8","hash":"36b4652672e714d0ba7f2e1e3a7fc215","time":"2019-12-02T01:25:55Z","shared":"yes","toread":"no","tags":""}]}