{"date":"2011-03-11T00:10:09Z","user":"ejfox","posts":[{"href":"http://www.propublica.org/article/how-i-passed-my-us-citizenship-test-by-keeping-the-right-answers-to-myself","description":"How I Passed My U.S. Citizenship Test: By Keeping the Right Answers to Myself - ProPublica","extended":"","meta":"63fdb8dcaf799ed7aca091fc7b74afab","hash":"9a090fc358aaa1ce8deee61a93dab5ae","time":"2011-03-11T00:10:09Z","shared":"yes","toread":"no","tags":""},{"href":"http://pseudoplacebo.tumblr.com/post/3777688706","description":"EJ Fox","extended":"Photo:  ","meta":"8ec96855845136d4f8614e6d1add271c","hash":"54768f0e0e8643e6570927d1bee43200","time":"2011-03-11T03:52:29Z","shared":"yes","toread":"no","tags":""},{"href":"http://www.npr.org/api/index","description":"API Overview : Tech Center : NPR","extended":"","meta":"2ee1966ea52a0dfb16dadc9d5c762bd6","hash":"092e96e28847a3ea1802037160e993cc","time":"2011-03-11T08:36:02Z","shared":"yes","toread":"no","tags":""},{"href":"http://www.museumofcorporateamerica.org/news/2011/3/8/sxsw-sneak-peak-our-freelance-future-infographic.html","description":"American Museum of American Corporate History - News - SXSW Sneak Peak! Our Freelance Future Infographic","extended":"If you're gonna be at #SXSW check out Solvate's booth for my 'Our Freelance Future' Infographic ","meta":"2e89d743f7c570bea06c21a973f4b36e","hash":"50ce226411af8190c2674ebe5086f6c4","time":"2011-03-11T16:18:45Z","shared":"yes","toread":"no","tags":""}]}