{"date":"2012-08-06T16:27:37Z","user":"ejfox","posts":[{"href":"http://enjalot.tumblr.com/post/28823336923/stacked-by-mrejfox-tributaryoftheday","description":"enjalot, Stacked by @mrejfox #tributaryoftheday","extended":"RT @enjalot: sunday's tributary of the day: \"Stacked\" by @mrejfox #tributaryoftheday ","meta":"ff693f620c8d709ae0acd0bacd7b45ae","hash":"1975303b99b96245618c5133bdf51dbf","time":"2012-08-06T16:27:37Z","shared":"yes","toread":"no","tags":""},{"href":"http://blog.ted.com/2012/08/06/5-rules-for-productive-conflict/","description":"TED Blog | 5 rules for productive conflict","extended":"RT @geekeasy: Everyone in #oo, especially the rebuilding the GA people should read this.  ","meta":"618f0c124e6e9030de5255bd52eaff63","hash":"9e0658bfda04612aa2484095bbb65c81","time":"2012-08-06T17:02:08Z","shared":"yes","toread":"no","tags":""}]}