{"date":"2015-07-31T14:15:05Z","user":"ejfox","posts":[{"href":"https://twitter.com/tjenningsbrown/status/627120301046919169/photo/1","description":"Jennings Brown on Twitter: \"Word? http://t.co/xKIjnrcofx\"","extended":"Word? ","meta":"25c20c4a57c38d830beae0d7bcf4d2fa","hash":"260a7c436baf29b15f795e7bb1bd9ca3","time":"2015-07-31T14:15:05Z","shared":"yes","toread":"no","tags":""},{"href":"https://twitter.com/TheOnion/status/627132488670953473/photo/1","description":"The Onion on Twitter: \"\"All that matters is that once you know what you want to do, you dive in a full 10 percent.\" http://t.co/EWZUCaKW3H http://t.co/u0q8OgzQgm\"","extended":"RT @TheOnion: \"All that matters is that once you know what you want to do, you dive in a full 10 percent.\"  ","meta":"439d1aba65edafef66d6f7c2eed463db","hash":"b0c16a7f51e6ce632fbb1a6cb5c9487a","time":"2015-07-31T15:07:06Z","shared":"yes","toread":"no","tags":""},{"href":"http://www.theonion.com/blogpost/find-the-thing-youre-most-passionate-about-then-do-31742","description":"Find The Thing You're Most Passionate About, Then Do It On Nights And Weekends For The Rest Of Your Life - The Onion - America's Finest News Source","extended":"RT @TheOnion: \"All that matters is that once you know what you want to do, you dive in a full 10 percent.\"  ","meta":"11dc734ce340d8b2afe21d899cc7bdc9","hash":"64dbafcd37e69eb489421836e4c1214f","time":"2015-07-31T15:07:06Z","shared":"yes","toread":"no","tags":""},{"href":"http://www.motherjones.com/politics/2015/07/homeland-security-surveillance-black-lives-matter","description":"Homeland Security Is Tracking Black Lives Matter. Is That Legal? | Mother Jones","extended":"RT @ACLU: Homeland Security is tracking #Blacklivesmatter. Is that legal?  via @motherjones @deray ","meta":"052e848b1c5959c6206c5bf7aa6e951d","hash":"4087aa168baf57a5b008d5f4165f9f98","time":"2015-07-31T15:56:08Z","shared":"yes","toread":"no","tags":""},{"href":"https://twitter.com/ACLU/status/626821572834263041/photo/1","description":"ACLU National on Twitter: \"Homeland Security is tracking #Blacklivesmatter. Is that legal? http://t.co/lJxZghkPKT via @motherjones @deray http://t.co/mxKNBXIqw6\"","extended":"RT @ACLU: Homeland Security is tracking #Blacklivesmatter. Is that legal?  via @motherjones @deray ","meta":"c9ed42421168c7c372c2ee2adf1ffd06","hash":"9e8a511f1eb7c27f5467d8bd08b754a5","time":"2015-07-31T15:56:08Z","shared":"yes","toread":"no","tags":""},{"href":"https://twitter.com/TravelingAnna/status/627207266547159040/photo/1","description":"Annemarie Dooling on Twitter: \"This is what I do to my coworkers. Btw we're hiring http://t.co/So5KEf6NMf\"","extended":"RT @TravelingAnna: This is what I do to my coworkers. Btw we're hiring ","meta":"19911de8854c5324ecdce0ab20152063","hash":"7fc2e1ff21e18b43dab789579e2ef04f","time":"2015-07-31T20:08:40Z","shared":"yes","toread":"no","tags":""},{"href":"https://twitter.com/OakSupplyCo/status/627210571872497664/photo/1","description":"Oakland Supply Co. on Twitter: \"Bay vibes. #oaksupplyco http://t.co/YnEmOUUz8i\"","extended":"RT @OakSupplyCo: Bay vibes. #oaksupplyco ","meta":"28e8c2932a2fe30d682f7aa894ea70d5","hash":"3b19b2763d6783178a9a49a3e0c59b82","time":"2015-07-31T20:19:38Z","shared":"yes","toread":"no","tags":""},{"href":"https://twitter.com/Cham10101/status/627234411503874048/photo/1","description":"Cham Green on Twitter: \"@justin_fenton The homicides are prevalent in neighborhoods with unemployment challenges. http://t.co/jYgyTFGl0G\"","extended":"RT @Cham10101: @justin_fenton The homicides are prevalent in neighborhoods with unemployment challenges. ","meta":"82d46552e7cd68a8e50a03fc55acb879","hash":"41a8513ca946c73e3e9d7420956a7ef6","time":"2015-07-31T22:05:21Z","shared":"yes","toread":"no","tags":""},{"href":"https://twitter.com/verge/status/627235826129346560","description":"The Verge on Twitter: \"Watch Kendrick Lamar as Uncle Sam in his \"For Free? (Interlude)\" music video http://t.co/POuYAySiVM http://t.co/NgJCJzb8eW\"","extended":"RT @sokane1: Kendrick is just hands down one of the most creative artists in the world right now ","meta":"a504e4e8fc3bce6d88463b33855b4383","hash":"a99be1a38983c97e7bfa885ce5448a38","time":"2015-07-31T22:08:28Z","shared":"yes","toread":"no","tags":""}]}