{"date":"2022-02-23T18:12:08Z","user":"ejfox","posts":[{"href":"https://twitter.com/yoyoel/status/1496544201705721865","description":"Yoel Roth on Twitter: \"We do not trigger automated enforcements based on report volume, ever, exactly because of how easily gamed that would be.\" / Twitter","extended":"","meta":"15e2366515cbcfebd14c8886e6d0ad7d","hash":"5d6ca4e65d4e464b0ef86e6bd616a1aa","time":"2022-02-23T18:12:08Z","shared":"yes","toread":"no","tags":""},{"href":"https://www.spotlightpa.org/news/2021/12/pennsylvania-redistricting-house-senate-districts-lookup-tool/","description":"Pa. redistricting maps: Search now to see your old and new political districts · Spotlight PA","extended":"","meta":"b9e28db28299e8611e92c83281ca3def","hash":"f3c958e051769db316d3252d3af9708d","time":"2022-02-23T22:59:47Z","shared":"yes","toread":"no","tags":""}]}