{"date":"2022-06-03T18:53:20Z","user":"ejfox","posts":[{"href":"https://medium.com/@derekkinsman/two-eh-42f0ee2152f1","description":"Two, eh.. The Second Amendment of the United… | by Derek J. Kinsman | Medium","extended":"","meta":"a6f9b08f66db718b9772589fa68af1c0","hash":"e4a188730b99dbbb9249375d6ed5f651","time":"2022-06-03T18:53:20Z","shared":"yes","toread":"no","tags":"politics"},{"href":"https://www.vulture.com/article/megan-stalter-profile.html","description":"The ‘Megan Stalter Character’ Is Its Own Comedy Genre Now","extended":"","meta":"05df3771d1cdad3248268e4f4f46586d","hash":"6ddba9c3086fb7c536229fbfee5f77a1","time":"2022-06-03T20:05:34Z","shared":"yes","toread":"no","tags":"comedy"}]}