{"date":"2011-05-20T01:36:17Z","user":"ejfox","posts":[{"href":"http://cloud.ejfox.com/6uoW","description":"TEMP-Image_1_1.png","extended":"Max makes some weird stuff in Illustrator sometimes: ","meta":"60c0c7f63359a558690afff02f8f732e","hash":"c98b39288de17bb40d346dbee170ba59","time":"2011-05-20T01:36:17Z","shared":"yes","toread":"no","tags":""},{"href":"http://www.zerply.com/profile/ejfox","description":"EJ Fox","extended":"Pretty slick! - I'm on @Zerply, check out my profile ","meta":"3d7200263706febf4d7c7fcedd201fa6","hash":"a1d6c815462c8c5a0b4ca505aae7dfaa","time":"2011-05-20T05:13:47Z","shared":"yes","toread":"no","tags":""},{"href":"http://stats.wikimedia.org/EN/TablesArticlesTotal.htm","description":"Wikipedia Statistics - Tables - Article count (official)","extended":"Look at this beautiful unintelligible craziness: ","meta":"2d332bc668fd5645d9c501a6ef3e73c9","hash":"a1f153e72ff1dcdba498bba3a7beb390","time":"2011-05-20T06:14:04Z","shared":"yes","toread":"no","tags":""}]}