{"date":"2011-01-16T00:22:14Z","user":"ejfox","posts":[{"href":"http://www.bluemic.com/yetipro/","description":"Blue Microphones | Yeti Pro - The Ultimate Professional USB Microphone w/ Built-In XLR Output","extended":"","meta":"5ee7aec4d311b4fdff6b98fe6f2b29c3","hash":"392d83ae878b843f66a5ece9ce97cfac","time":"2011-01-16T00:22:14Z","shared":"yes","toread":"no","tags":""},{"href":"http://nymag.com/daily/entertainment/2011/01/read_bill_murrays_hilarious_sp.html","description":"Read Bill Murray’s Hilarious Speech to Sofia Coppola at the NBR Awards -- Vulture","extended":"","meta":"1d61c0121216f9ebab9102c026095106","hash":"d84665ad91b41c6fccb0581aca4dfc61","time":"2011-01-16T04:34:31Z","shared":"yes","toread":"no","tags":""},{"href":"http://hackvan.com/etext/how-i-got-my-diy-degree.html","description":"How I Got my D.I.Y. Degree ... at the University of Planet Earth","extended":"How I Got my D.I.Y. Degree ... at the University of Planet Earth ","meta":"d6c4a360cea6131f2aa4d4054ec49412","hash":"ad617e4b54afd84f7ae67da006fedf97","time":"2011-01-16T04:35:03Z","shared":"yes","toread":"no","tags":""}]}