{"date":"2011-03-15T06:24:45Z","user":"ejfox","posts":[{"href":"http://kops.ub.uni-konstanz.de/volltexte/2008/7046/pdf/TVCG00.pdf","description":"TVCG00.pdf","extended":"","meta":"030a8babae603f2c9e06cdbc1debf0e7","hash":"9f971020e3594d11a72ad40e339390b3","time":"2011-03-15T06:24:45Z","shared":"yes","toread":"no","tags":""},{"href":"http://fellinlovewithdata.com/guides/7-classic-foundational-vis-papers","description":"7 Classic Foundational Vis Papers You Might not Want to Publicly Confess you Don’t Know — Fell in Love with Data","extended":"","meta":"281df1411a9781fe1873034012368356","hash":"adcae6cb31081209167ea97667d104e3","time":"2011-03-15T06:29:33Z","shared":"yes","toread":"no","tags":""},{"href":"http://en.wikipedia.org/wiki/Great-circle_distance","description":"Great-circle distance - Wikipedia, the free encyclopedia","extended":"","meta":"95d114b76b71ba09cf616c9c30070318","hash":"a2ca62d6cd2c0a2f5a17e012c7639347","time":"2011-03-15T06:36:59Z","shared":"yes","toread":"no","tags":""},{"href":"http://newyork.grubstreet.com/2010/07/pre-order_modernist_cuisine_na.html","description":"Modernist Cuisine, Nathan Myhrvold’s 2,200-Page Cookbook, Is Finally Ready -- Grub Street New York","extended":"","meta":"21dbf6ab6deddafc1ee0cd1f2449e036","hash":"0843b7a59c682965184f426f88c2840c","time":"2011-03-15T07:10:29Z","shared":"yes","toread":"no","tags":""}]}