{"date":"2012-10-06T01:06:33Z","user":"ejfox","posts":[{"href":"http://dribbble.com/shots/673757-Typical-price","description":"Dribbble - Typical price by ssh4","extended":"@simplify could you consider making this your new iPhone icon? =] Money icon by @ssh4net on @dribbble: ","meta":"2afd86dd483cd3b075a52d3306ce40bd","hash":"693774ed110d092f8d0169465d98cf22","time":"2012-10-06T01:06:33Z","shared":"yes","toread":"no","tags":""},{"href":"http://www.modernissta.com/2011/06/dieter-rams%E2%80%99-disciplined-simplicity/","description":"Dieter Rams’ Disciplined Simplicity - Modernissta","extended":"","meta":"947967c7827beec08589edef710ad719","hash":"5c1df0cb5269554c1aea79b3bc22f51b","time":"2012-10-06T19:35:17Z","shared":"yes","toread":"no","tags":""},{"href":"http://www.niemanlab.org/2012/09/brian-boyer-welcome-to-hacker-journalism-101-take-your-seats/","description":"Brian Boyer: Welcome to Hacker Journalism 101, take your seats » Nieman Journalism Lab","extended":"","meta":"4725389b529f0f2f7d7b80e9d579a08e","hash":"52a78ee97ff0740b3738fcc5556997e9","time":"2012-10-06T19:49:56Z","shared":"yes","toread":"no","tags":""},{"href":"http://t.co/Hk58KPUo","description":"Square and Circle: The Logic of Occupy – The New Inquiry","extended":"","meta":"b1b9bdb3a5b26801d4dab4cdeab43a6b","hash":"d7ba34d5f2b4b275473de47cf1e28404","time":"2012-10-06T19:50:03Z","shared":"yes","toread":"no","tags":""},{"href":"http://www.smithsonianmag.com/arts-culture/How-Steve-Jobs-Love-of-Simplicity-Fueled-A-Design-Revolution-166251016.html#ixzz26UVfNQgl","description":"How Steve Jobs' Love of Simplicity Fueled A Design Revolution | Arts & Culture | Smithsonian Magazine","extended":"","meta":"5150ab314375564268ac7179c22c1610","hash":"316d9450fe439a36327c60c6c11d305b","time":"2012-10-06T23:40:37Z","shared":"yes","toread":"no","tags":""}]}