{"date":"2015-02-11T15:06:30Z","user":"ejfox","posts":[{"href":"https://twitter.com/turnislefthome/status/565527302856245248/photo/1","description":"Timothy J. Reynolds on Twitter: \"Some fella named Ryan emailed me this with no description, just this glorious pic. Maybe he wants me to build it. http://t.co/zUFkS8c4EH\"","extended":"Some fella named Ryan emailed me this with no description, just this glorious pic. Maybe he wants me to build it. ","meta":"dfb933ab8abb2eb5193974ab7e375216","hash":"0f43070fb58cfa47a71ee69ded4b20a1","time":"2015-02-11T15:06:30Z","shared":"yes","toread":"no","tags":""},{"href":"https://twitter.com/claytoncubitt/status/565585959820222465/photo/1","description":"Clayton Cubitt on Twitter: \"February is the realest month in NYC. No illusion remains. http://t.co/sRE58Vihb8 http://t.co/sFh2KfCyFO\"","extended":"RT @claytoncubitt: February is the realest month in NYC. No illusion remains.  ","meta":"15b1641e5a331c4fad4fa5092c9f82c5","hash":"c94dc997a331587ff1ee31c83a04c88c","time":"2015-02-11T19:05:42Z","shared":"yes","toread":"no","tags":""},{"href":"http://instagram.com/p/y-KTbbJXq_/","description":"Instagram","extended":"RT @claytoncubitt: February is the realest month in NYC. No illusion remains.  ","meta":"a162a736a9bd2dcf115e823dd35c5edb","hash":"f1c71b1fef577a4dce1e9d986bc5b208","time":"2015-02-11T19:05:42Z","shared":"yes","toread":"no","tags":""},{"href":"http://www.motherjones.com/media/2015/02/joey-badass-new-video-premiere-like-me-police-brutality","description":"In a New Video, Joey Bada$$ Takes on Police Shootings of Unarmed Black Men | Mother Jones","extended":"RT @MichaelMechanic: In a new video, rising young rapper @joeyBADASS tackles police shootings of unarmed black men.  ","meta":"34fa80706552d83a7a8b15a68134391b","hash":"01d7b5298e4e20cd5a13b4eca2f2696f","time":"2015-02-11T19:43:33Z","shared":"yes","toread":"no","tags":""},{"href":"https://twitter.com/MichaelMechanic/status/565593309067104258/photo/1","description":"Michael Mechanic on Twitter: \"In a new video, rising young rapper @joeyBADASS tackles police shootings of unarmed black men. http://t.co/JxuCX0xW13 http://t.co/cRj2uSB2vZ\"","extended":"RT @MichaelMechanic: In a new video, rising young rapper @joeyBADASS tackles police shootings of unarmed black men.  ","meta":"9e5387fe5607bd48de7d3a5ffe015070","hash":"4fb748e1590cc088681b4a17a0528682","time":"2015-02-11T19:43:33Z","shared":"yes","toread":"no","tags":""},{"href":"http://www.vox.com/2015/2/11/8022017/house-of-cards-season-3","description":"Netflix accidentally uploaded season 3 of House of Cards — then took it right down - Vox","extended":"RT @voxdotcom: Season 3 of House Of Cards miraculously now on Netflix  ","meta":"5e149b1088efecf89f62c9aa2bae30bc","hash":"64a96c050cf1a77756a01b6e04d82257","time":"2015-02-11T21:44:43Z","shared":"yes","toread":"no","tags":""},{"href":"https://twitter.com/voxdotcom/status/565627111558631424/photo/1","description":"Vox on Twitter: \"Season 3 of House Of Cards miraculously now on Netflix http://t.co/ze8DWucdA0 http://t.co/po4AOjbSBg\"","extended":"RT @voxdotcom: Season 3 of House Of Cards miraculously now on Netflix  ","meta":"2a345bcd606ef513cda623ba30d3c337","hash":"9a41692078f5e89c887277f25296b401","time":"2015-02-11T21:44:43Z","shared":"yes","toread":"no","tags":""},{"href":"https://twitter.com/Circa/status/565629388864385026/photo/1","description":"Circa on Twitter: \"Third season of 'House of Cards' released two weeks early, quickly taken down: http://t.co/x97pk1euck http://t.co/LUF7TmQ9xj\"","extended":"RT @Circa: Third season of 'House of Cards' released two weeks early, quickly taken down:  ","meta":"23318d94455b06e09e13a3db21edcc1b","hash":"a020b1895b5da7b606a7b5d8b2949f9a","time":"2015-02-11T21:53:31Z","shared":"yes","toread":"no","tags":""},{"href":"http://cir.ca/news/netflixs-house-of-cards","description":"Third season of 'House of Cards' released two weeks early, quickly taken down | Circa News","extended":"RT @Circa: Third season of 'House of Cards' released two weeks early, quickly taken down:  ","meta":"ff764557ab1a97e1120f27d8bd2ae24f","hash":"e3411b26713501509822634054b69d0e","time":"2015-02-11T21:53:31Z","shared":"yes","toread":"no","tags":""},{"href":"http://i.imgur.com/FImcPiG.png","description":"Untitled (http://i.imgur.com/FImcPiG.png)","extended":"RT @rtkrum: RT @VizWorld: Word cloud of the top 1000 most common passwords  #dataviz #passwords #WordCloud ","meta":"87a5457893e917ce7f47d12799859bb2","hash":"f7ca31ea381ba21ec8e3958b1b94ea2d","time":"2015-02-11T21:54:53Z","shared":"yes","toread":"no","tags":""},{"href":"https://twitter.com/rtkrum/status/565630015124303876/photo/1","description":"Randy Krum on Twitter: \"RT @VizWorld: Word cloud of the top 1000 most common passwords http://t.co/Tb1kOmf3xO #dataviz #passwords #WordCloud http://t.co/u9qodvQ3Pn\"","extended":"RT @rtkrum: RT @VizWorld: Word cloud of the top 1000 most common passwords  #dataviz #passwords #WordCloud ","meta":"dffc65be6fb002bf2201269576ad96b4","hash":"6999a4622f1fdac4fd217ed1b7f328bd","time":"2015-02-11T21:54:53Z","shared":"yes","toread":"no","tags":""}]}