{"date":"2015-04-09T02:26:31Z","user":"ejfox","posts":[{"href":"https://twitter.com/gelicia/status/585992153727401984/photo/1","description":"Kristina on Twitter: \"Put a clothesline collage held up by 3d printed hands to decorate my living room and I'm far too pleased with myself http://t.co/oo1shXlv30\"","extended":"Put a clothesline collage held up by 3d printed hands to decorate my living room and I'm far too pleased with myself ","meta":"8fde937c768edd2252c8d19024239f66","hash":"9af861ab57401b32627d93d8707a5d36","time":"2015-04-09T02:26:31Z","shared":"yes","toread":"no","tags":""},{"href":"https://twitter.com/gelicia/status/585992153727401984","description":"Kristina on Twitter: \"Put a clothesline collage held up by 3d printed hands to decorate my living room and I'm far too pleased with myself http://t.co/oo1shXlv30\"","extended":"The coolest ","meta":"523d5458b7ea747f333c998fd83c6730","hash":"d02f28c32ab992eeb6ba544738f687f7","time":"2015-04-09T02:34:53Z","shared":"yes","toread":"no","tags":""},{"href":"https://twitter.com/Newmanology/status/586152605241450499/photo/1","description":"Robert Newman on Twitter: \"BLACK LIVES MATTER cover of the new @TIME magazine. http://t.co/YSs1vSwswj\"","extended":"RT @Newmanology: BLACK LIVES MATTER cover of the new @TIME magazine. ","meta":"e632fbd4e94e75b3fd5cbb323c3c8f9d","hash":"8ff9780681621bdaf94849896ed701a3","time":"2015-04-09T13:21:08Z","shared":"yes","toread":"no","tags":""},{"href":"https://twitter.com/HuhWhatandWhere/status/586184956948258816/photo/1","description":"HW&W Recordings on Twitter: \".@GoldLink announces North American tour for this summer http://t.co/lRsvHBjSyF\"","extended":".@GoldLink announces North American tour for this summer ","meta":"d093ea08d8bded9bd8f037c04d1ed90b","hash":"696fa44c3b6b9500201244768f4466ff","time":"2015-04-09T15:12:39Z","shared":"yes","toread":"no","tags":""},{"href":"https://twitter.com/YousefMunayyer/status/586184749103845377/photo/1","description":"Yousef Munayyer on Twitter: \"So the Times of Israel ran this\n\nhttps://t.co/v6XOc3Oqi9 http://t.co/NEE1Nh5cD9\"","extended":"RT @YousefMunayyer: So the Times of Israel ran this\n\n ","meta":"80f0c19a4ac4e513282c66a5b2888cf3","hash":"0ea045953419deeed68e08f828c7c2a6","time":"2015-04-09T17:10:37Z","shared":"yes","toread":"no","tags":""},{"href":"https://archive.today/bUarE","description":"Understanding the Idea of Israeli Land Under Talmudic Law | Josh Bornstein | The Blogs | The Times of Israel","extended":"RT @YousefMunayyer: So the Times of Israel ran this\n\n ","meta":"cabf7a1fc4f152fee2d4587f3d1e4d33","hash":"648a0a79f1a8910916e30263d1bfce75","time":"2015-04-09T17:10:37Z","shared":"yes","toread":"no","tags":""},{"href":"https://twitter.com/mrejfox/status/586282775453499395/photo/1","description":"EJ Fox on Twitter: \"the resident @vocativ punmaster general never disappoints http://t.co/utb8wcydQB\"","extended":"the resident @vocativ punmaster general never disappoints ","meta":"2574e45ffbacaa4405c1776de1f4bd32","hash":"09f0b485178c672ccec97cd3ee0f6e4a","time":"2015-04-09T21:41:20Z","shared":"yes","toread":"no","tags":""}]}